.long-description.html
README.rst
setup.py
src/collective/__init__.py
src/collective.behavior.price.egg-info/PKG-INFO
src/collective.behavior.price.egg-info/SOURCES.txt
src/collective.behavior.price.egg-info/dependency_links.txt
src/collective.behavior.price.egg-info/entry_points.txt
src/collective.behavior.price.egg-info/namespace_packages.txt
src/collective.behavior.price.egg-info/not-zip-safe
src/collective.behavior.price.egg-info/requires.txt
src/collective.behavior.price.egg-info/top_level.txt
src/collective/behavior/__init__.py
src/collective/behavior/price/__init__.py
src/collective/behavior/price/behavior.py
src/collective/behavior/price/configure.zcml
src/collective/behavior/price/interfaces.py
src/collective/behavior/price/schema.py
src/collective/behavior/price/upgrades.py
src/collective/behavior/price/upgrades.zcml
src/collective/behavior/price/Extensions/Install.py
src/collective/behavior/price/Extensions/__init__.py
src/collective/behavior/price/docs/CONTRIBUTORS.rst
src/collective/behavior/price/docs/CREDITS.rst
src/collective/behavior/price/docs/HISTORY.rst
src/collective/behavior/price/docs/LICENSE.rst
src/collective/behavior/price/locales/collective.behavior.price.pot
src/collective/behavior/price/locales/fi/LC_MESSAGES/collective.behavior.price.mo
src/collective/behavior/price/locales/fi/LC_MESSAGES/collective.behavior.price.po
src/collective/behavior/price/profiles/default/catalog.xml
src/collective/behavior/price/profiles/default/metadata.xml
src/collective/behavior/price/profiles/default/registry.xml
src/collective/behavior/price/profiles/uninstall/registry.xml
src/collective/behavior/price/tests/__init__.py
src/collective/behavior/price/tests/base.py
src/collective/behavior/price/tests/test_ICurrency.py
src/collective/behavior/price/tests/test_IPrice.py
src/collective/behavior/price/tests/test_Price.py
src/collective/behavior/price/tests/test_setup.py
src/collective/behavior/price/tests/test_upgrades.py