Metadata-Version: 1.1
Name: collective.behavior.price
Version: 0.4
Summary: Behavior to make content pricing.
Home-page: https://github.com/collective/collective.behavior.price/
Author: Taito Horiuchi
Author-email: taito.horiuchi@gmail.com
License: BSD
Platform: UNKNOWN
Classifier: Framework :: Plone
Classifier: Framework :: Plone :: 4.3
Classifier: License :: OSI Approved :: BSD License
Classifier: Programming Language :: Python
Classifier: Programming Language :: Python :: 2.7
